fsm_admin2/__init__.py
fsm_admin2/admin.py
fsm_admin2/apps.py
fsm_admin2/templates/fsm_admin2/fsm_transition_buttons.html
fsm_admin2/templates/fsm_admin2/fsm_transition_form.html
django_fsm_admin2-0.1.3.dist-info/LICENSE
django_fsm_admin2-0.1.3.dist-info/METADATA
django_fsm_admin2-0.1.3.dist-info/WHEEL
django_fsm_admin2-0.1.3.dist-info/top_level.txt
django_fsm_admin2-0.1.3.dist-info/RECORD
